pwconn/__init__.py
pwconn/alsa_info.py
pwconn/pw_info.py
pwconn/pwconn.py
pwconn/pwconn.tcss
pwconn-0.6.0.dist-info/WHEEL
pwconn-0.6.0.dist-info/entry_points.txt
pwconn-0.6.0.dist-info/METADATA
pwconn-0.6.0.dist-info/RECORD
