Metadata-Version: 2.4
Name: pwconn
Version: 0.6.0
Summary: Manage Pipewire connections via a TUI
Author: Bill Gribble
Author-email: Bill Gribble <grib@billgribble.com>
License-Expression: GPL-2.0
Classifier: Development Status :: 3 - Alpha
Classifier: Environment :: Console
Classifier: Programming Language :: Python
Classifier: Topic :: Multimedia :: Sound/Audio
Requires-Dist: textual>=5.3.0
Requires-Dist: textual-dev>=1.7.0
Requires-Python: >=3.11
